Metadata-Version: 2.1
Name: ttsi
Version: 0.0.5
Summary: Send reports by email
Home-page: https://github.com/dacker-team/ttsi
Author: Dacker
Author-email: hello@dacker.co
License: UNKNOWN
Keywords: easily send reports email bi data
Platform: UNKNOWN
Classifier: Programming Language :: Python :: 3
Classifier: License :: OSI Approved :: MIT License
Classifier: Operating System :: OS Independent
Requires-Python: >=3
License-File: LICENSE
